LICENSE
MANIFEST.in
README.rst
setup.py
django_robots_txt.egg-info/PKG-INFO
django_robots_txt.egg-info/SOURCES.txt
django_robots_txt.egg-info/dependency_links.txt
django_robots_txt.egg-info/requires.txt
django_robots_txt.egg-info/top_level.txt
django_robots_txt.egg-info/zip-safe
robots_txt/__init__.py
robots_txt/models.py
robots_txt/tests.py
robots_txt/urls.py
robots_txt/views.py
robots_txt/templates/robots_txt/robots.txt