Metadata-Version: 1.1
Name: django-robots-txt
Version: 0.3
Summary: Simple robots.txt app for django
Home-page: http://github.com/nkuttler/django-robots-txt
Author: Nicolas Kuttler
Author-email: pypi@nicolaskuttler.com
License: BSD
Platform: UNKNOWN
Classifier: Development Status :: 4 - Beta
Classifier: Environment :: Web Environment
Classifier: Intended Audience :: Developers
Classifier: License :: OSI Approved :: BSD License
Classifier: Operating System :: OS Independent
Classifier: Programming Language :: Python
Classifier: Framework :: Django
